[
  {
    "id": "prod_1",
    "nom": "Corsair One i500",
    "description": "PC gaming ultra compact avec RTX 5090 et refroidissement liquide.",
    "prix": "À partir de 3 499 €",
    "categorie": "PC GAMING",
    "image": "assets/images/Corsair One i500 sty.png",
    "lien": "/frontend/src/pages/fiches/Corsair One i500.html",
    "top_du_mois": true,
    "stock": "disponible",
    "tags": [],
    "date_ajout": "2025-08-07"
  },
  {
    "id": "prod_2",
    "nom": "Vibox X-215 SG",
    "description": "PC gaming haut de gamme avec éclairage RGB, conçu pour les performances en 4K et la réalité virtuelle.",
    "prix": "1549.99 €",
    "categorie": "PC GAMING",
    "image": "assets/images/Vibox X-215 SG stylé.png",
    "lien": "/frontend/src/pages/fiches/ViboxX-215SG.html",
    "top_du_mois": true,
    "stock": "disponible",
    "tags": [],
    "date_ajout": "2025-08-07"
  },
  {
    "id": "prod_3",
    "nom": "Asus ROG Strix G18",
    "description": "PC 18 pouces ultra puissant avec RTX 5070 et écran 240 Hz.",
    "prix": "À partir de 2 599 €",
    "categorie": "PC GAMING",
    "image": "assets/images/Asus ROG Strix G18 2.png",
    "lien": "/frontend/src/pages/fiches/Asus ROG Strix G18.html",
    "top_du_mois": true,
    "stock": "disponible",
    "tags": [],
    "date_ajout": "2025-08-07"
  },
  {
    "id": "prod_4",
    "nom": "Dell PowerEdge R960",
    "description": "Serveur rack 4U avec 4 processeurs et 12 To de RAM.",
    "prix": "À partir de 8 999 €",
    "categorie": "SERVEUR",
    "image": "assets/images/dell-poweredge-r960.png",
    "lien": "/frontend/src/pages/fiches/Dell PowerEdge R960.html",
    "top_du_mois": false,
    "stock": "disponible",
    "tags": [],
    "date_ajout": "2025-08-07"
  },
  {
    "id": "prod_5",
    "nom": "Dell PowerEdge R760",
    "description": "Serveur rack 2U ultra performant pour datacenter et virtualisation.",
    "prix": "À partir de 4 999 €",
    "categorie": "SERVEUR",
    "image": "assets/images/Dell PowerEdge R760.png",
    "lien": "/frontend/src/pages/fiches/Dell PowerEdge R760.html",
    "top_du_mois": false,
    "stock": "disponible",
    "tags": [],
    "date_ajout": "2025-08-07"
  },
  {
    "id": "prod_6",
    "nom": "Logitech MX Master 4S",
    "description": "Souris ergonomique ultra précise pour bureautique et gaming.",
    "prix": "À partir de 149 €",
    "categorie": "PERIPHERIQUES",
    "image": "assets/images/logitech-mx-master-4s.png",
    "lien": "/frontend/src/pages/fiches/Logitech MX Master 4S.html",
    "top_du_mois": false,
    "stock": "disponible",
    "tags": [],
    "date_ajout": "2025-08-07"
  },
  {
    "id": "prod_7",
    "nom": "SteelSeries Apex Pro TKL Gen 3",
    "description": "Clavier gaming mécanique ultra réactif avec switches magnétiques ajustables et OLED intégré.",
    "prix": "À partir de 229 €",
    "categorie": "PERIPHERIQUES",
    "image": "assets/images/SteelSeries Apex Pro TKL Gen 3.png",
    "lien": "/frontend/src/pages/fiches/SteelSeries Apex Pro TKL Gen 3.html",
    "top_du_mois": false,
    "stock": "disponible",
    "tags": [],
    "date_ajout": "2025-08-07"
  },
  {
    "id": "prod_8",
    "nom": "Apple iPad Pro M4",
    "description": "Tablette professionnelle avec puce M4, écran OLED et Face ID.",
    "prix": "À partir de 1 099 €",
    "categorie": "TABLETTE",
    "image": "assets/images/iPad.png",
    "lien": "/frontend/src/pages/fiches/Apple iPad Pro M4.html",
    "top_du_mois": false,
    "stock": "disponible",
    "tags": [],
    "date_ajout": "2025-08-07"
  },
  {
    "id": "prod_9",
    "nom": "Samsung Galaxy S25 Ultra",
    "description": "Smartphone haut de gamme avec zoom x100 et écran AMOLED 120Hz.",
    "prix": "À partir de 1 199 €",
    "categorie": "SMARTPHONE",
    "image": "assets/images/Samsung Galaxy S25 U.png",
    "lien": "/frontend/src/pages/fiches/Samsung Galaxy S25 Ultra.html",
    "top_du_mois": false,
    "stock": "disponible",
    "tags": [],
    "date_ajout": "2025-08-07"
  },
  {
    "id": "prod_10",
    "nom": "Garmin Fénix 8",
    "description": "Montre GPS multisport avec cartographie et suivi santé complet.",
    "prix": "À partir de 799 €",
    "categorie": "MONTRE CONNECTE",
    "image": "assets/images/fénix 8.png",
    "lien": "/frontend/src/pages/fiches/Garmin Fénix 8.html",
    "top_du_mois": false,
    "stock": "disponible",
    "tags": [],
    "date_ajout": "2025-08-07"
  },
  {
    "id": "prod_11",
    "nom": "LG OLED65 G5",
    "description": "TV OLED 4K 65'' avec Dolby Vision, G-Sync et design mural.",
    "prix": "À partir de 2 790 €",
    "categorie": "ECRAN TV",
    "image": "assets/images/lg.png",
    "lien": "/frontend/src/pages/fiches/LG OLED65 G5.html",
    "top_du_mois": false,
    "stock": "disponible",
    "tags": [],
    "date_ajout": "2025-08-07"
  },
  {
    "id": "prod_12",
    "nom": "LG OLED65 G3",
    "description": "Téléviseur OLED EVO 4K ultra-fin avec Dolby Vision et 120Hz.",
    "prix": "À partir de 2 999 €",
    "categorie": "ECRAN TV",
    "image": "assets/images/LG OLED65 G3.png",
    "lien": "/frontend/src/pages/fiches/LG OLED65 G3.html",
    "top_du_mois": false,
    "stock": "disponible",
    "tags": [],
    "date_ajout": "2025-08-07"
  },
  {
    "id": "prod_13",
    "nom": "Insta360 X5",
    "description": "Caméra 360 professionnelle pour capture immersive en 8K.",
    "prix": "À partir de 549 €",
    "categorie": "CAMERA",
    "image": "assets/images/Insta X.png",
    "lien": "/frontend/src/pages/fiches/Insta360 X5.html",
    "top_du_mois": false,
    "stock": "disponible",
    "tags": [],
    "date_ajout": "2025-08-07"
  },
  {
    "id": "prod_14",
    "nom": "Canon EOS R6 Mark II",
    "description": "Appareil photo hybride plein format ultra rapide, idéal pour les créateurs photo/vidéo.",
    "prix": "À partir de 2 899 €",
    "categorie": "CAMERA",
    "image": "assets/images/Canon EOS R6 Mark II.png",
    "lien": "/frontend/src/pages/fiches/Canon EOS R6 Mark II.html",
    "top_du_mois": false,
    "stock": "disponible",
    "tags": [],
    "date_ajout": "2025-08-07"
  },
  {
    "id": "prod_15",
    "nom": "Valerion Vision Master Pro 2",
    "description": "Vidéoprojecteur laser 4K HDR avec 3500 lumens et Android TV intégré.",
    "prix": "À partir de 2 999 €",
    "categorie": "VIDEO PROJECTEUR",
    "image": "assets/images/Valerion Vision Mast.png",
    "lien": "/frontend/src/pages/fiches/Valerion Vision Master Pro 2.html",
    "top_du_mois": false,
    "stock": "disponible",
    "tags": [],
    "date_ajout": "2025-08-07"
  },
  {
    "id": "prod_16",
    "nom": "Epson EH-LS12000B",
    "description": "Vidéoprojecteur laser 4K Pro-UHD haut de gamme avec HDR10+ et installation flexible.",
    "prix": "À partir de 4 195 €",
    "categorie": "VIDEO PROJECTEUR",
    "image": "assets/images/Epson EH-LS12000B.png",
    "lien": "/frontend/src/pages/fiches/Epson EH-LS12000B.html",
    "top_du_mois": false,
    "stock": "disponible",
    "tags": [],
    "date_ajout": "2025-08-07"
  },
  {
    "id": "prod_17",
    "nom": "Freebox Ultra",
    "description": "Box ultra rapide avec fibre 8G, WiFi 7 et services TV premium.",
    "prix": "À partir de 49,99 €",
    "categorie": "BOX INTERNET",
    "image": "assets/images/Freebox Ultra stylé.png",
    "lien": "/frontend/src/pages/fiches/Freebox Ultra.html",
    "top_du_mois": false,
    "stock": "disponible",
    "tags": [],
    "date_ajout": "2025-08-07"
  },
  {
    "id": "prod_18",
    "nom": "Bose QuietComfort 45",
    "description": "Casque à réduction de bruit actif et autonomie prolongée.",
    "prix": "À partir de 349 €",
    "categorie": "CASQUE AUDIO",
    "image": "assets/images/Bose QuietComfort 45.png",
    "lien": "/frontend/src/pages/fiches/Bose QuietComfort 45.html",
    "top_du_mois": false,
    "stock": "disponible",
    "tags": [],
    "date_ajout": "2025-08-07"
  },
  {
    "id": "prod_19",
    "nom": "Sony WH-1000XM5",
    "description": "Casque sans fil haut de gamme avec réduction de bruit active et audio haute résolution.",
    "prix": "À partir de 419 €",
    "categorie": "CASQUE AUDIO",
    "image": "assets/images/Sony WH-1000XM5.png",
    "lien": "/frontend/src/pages/fiches/Sony WH-1000XM5.html",
    "top_du_mois": false,
    "stock": "disponible",
    "tags": [],
    "date_ajout": "2025-08-07"
  },
  {
    "id": "prod_20",
    "nom": "Samsung Flip Pro 2025",
    "description": "Tableau interactif 75'' tactile avec stylet et écran QLED.",
    "prix": "À partir de 2 199 €",
    "categorie": "TABLEAU INTERACTIF",
    "image": "assets/images/samsung flip pro.png",
    "lien": "/frontend/src/pages/fiches/Samsung Flip Pro 2025.html",
    "top_du_mois": false,
    "stock": "disponible",
    "tags": [],
    "date_ajout": "2025-08-07"
  },
  {
    "id": "prod_21",
    "nom": "HKMLC Smart Board Explorer Elite Dual 75",
    "description": "Tableau interactif 4K UHD avec double système Android/Windows, idéal pour l’éducation et les entreprises.",
    "prix": "À partir de 3 599 €",
    "categorie": "TABLEAU INTERACTIF",
    "image": "assets/images/HKMLC Smart Board Explorer Elite Dual 75.png",
    "lien": "/frontend/src/pages/fiches/HKMLC Smart Board Explorer Elite Dual 75.html",
    "top_du_mois": false,
    "stock": "disponible",
    "tags": [],
    "date_ajout": "2025-08-07"
  },
  {
    "id": "prod_22",
    "nom": "Asus ROG Ally X",
    "description": "Console portable Windows puissante et ergonomique pour gamers exigeants.",
    "prix": "À partir de 899 €",
    "categorie": "CONSOLE",
    "image": "assets/images/ROG Ally.png",
    "lien": "/frontend/src/pages/fiches/Asus ROG Ally X.html",
    "top_du_mois": false,
    "stock": "disponible",
    "tags": [],
    "date_ajout": "2025-08-07"
  },
  {
    "id": "prod_23",
    "nom": "Meta Quest 3",
    "description": "Casque de réalité mixte haut de gamme avec passthrough HD.",
    "prix": "À partir de 549 €",
    "categorie": "CASQUE VR",
    "image": "assets/images/Meta Quest 3.png",
    "lien": "/frontend/src/pages/fiches/Meta Quest 3.html",
    "top_du_mois": false,
    "stock": "disponible",
    "tags": [],
    "date_ajout": "2025-08-07"
  },
  {
    "id": "prod_24",
    "nom": "Creality Ender 5 Neo",
    "description": "Imprimante 3D précise avec double axe Z et auto-nivellement.",
    "prix": "À partir de 399 €",
    "categorie": "IMPRIMANTE 3D",
    "image": "assets/images/imprimante 3D.png",
    "lien": "/frontend/src/pages/fiches/Creality Ender 5 Neo.html",
    "top_du_mois": false,
    "stock": "disponible",
    "tags": [],
    "date_ajout": "2025-08-07"
  },
  {
    "id": "prod_25",
    "nom": "Creality Ender 3 V3",
    "description": "Imprimante 3D précise avec double axe Z et auto-nivellement.",
    "prix": "329,00 €",
    "categorie": "IMPRIMANTE 3D",
    "image": "assets/images/Creality Ender 3 V3 stylé.png",
    "lien": "/frontend/src/pages/fiches/CrealityEnder3V3.html",
    "top_du_mois": false,
    "stock": "disponible",
    "tags": [],
    "date_ajout": "2025-08-07"
  },
  {
    "id": "prod_26",
    "nom": "Creality Halot Mage S 14K",
    "description": "Imprimante 3D résine ultra précise avec écran 14K, purification d’air et impression rapide Dynax+.",
    "prix": "À partir de 562 €",
    "categorie": "IMPRIMANTE 3D",
    "image": "assets/images/Creality Halot Mage S 14K.png",
    "lien": "/frontend/src/pages/fiches/Creality Halot Mage S 14K.html",
    "top_du_mois": false,
    "stock": "disponible",
    "tags": [],
    "date_ajout": "2025-08-07"
  },
  {
    "id": "prod_27",
    "nom": "DJI Mavic 4 Pro",
    "description": "Drone ultra stabilisé avec capteurs 360° et caméra 6K.",
    "prix": "À partir de 1 799 €",
    "categorie": "DRONE",
    "image": "assets/images/DJI Mavic 4 Pro styl.png",
    "lien": "/frontend/src/pages/fiches/DJI Mavic 4 Pro.html",
    "top_du_mois": false,
    "stock": "disponible",
    "tags": [],
    "date_ajout": "2025-08-07"
  },
  {
    "id": "prod_28",
    "nom": "Skydio X10",
    "description": "Drone autonome intelligent avec caméra thermique et stabilisation avancée.",
    "prix": "À partir de 2 999 €",
    "categorie": "DRONE",
    "image": "assets/images/Skydio X10.png",
    "lien": "/frontend/src/pages/fiches/Skydio X10.html",
    "top_du_mois": false,
    "stock": "disponible",
    "tags": [],
    "date_ajout": "2025-08-07"
  },
  {
    "id": "prod_29",
    "nom": "DJI Air 3S",
    "description": "Drone polyvalent pour créateurs de contenu, avec double capteur et détection LiDAR.",
    "prix": "À partir de 1 599 €",
    "categorie": "DRONE",
    "image": "assets/images/DJI Air 3S.png",
    "lien": "/frontend/src/pages/fiches/DJI Air 3S.html",
    "top_du_mois": false,
    "stock": "disponible",
    "tags": [],
    "date_ajout": "2025-08-07"
  },
  {
    "id": "prod_30",
    "nom": "Parrot Anafi USA",
    "description": "Drone professionnel avec zoom x32 et capteur thermique pour missions critiques.",
    "prix": "À partir de 2 699 €",
    "categorie": "DRONE",
    "image": "assets/images/Parrot Anafi USA.png",
    "lien": "/frontend/src/pages/fiches/Parrot Anafi USA.html",
    "top_du_mois": false,
    "stock": "disponible",
    "tags": [],
    "date_ajout": "2025-08-07"
  },
  {
    "id": "prod_31",
    "nom": "DJI Mini 5 Pro",
    "description": "Drone ultra-léger avec capteur 1” et détection LiDAR omnidirectionnelle.",
    "prix": "À partir de 999 €",
    "categorie": "DRONE",
    "image": "assets/images/DJI Mini 5 Pro.png",
    "lien": "/frontend/src/pages/fiches/DJI Mini 5 Pro.html",
    "top_du_mois": false,
    "stock": "disponible",
    "tags": [],
    "date_ajout": "2025-08-07"
  },
  {
    "id": "prod_32",
    "nom": "Autel Nano+",
    "description": "Mini drone puissant et nomade, avec capteur 50 MP et zoom x16.",
    "prix": "À partir de 849 €",
    "categorie": "DRONE",
    "image": "assets/images/Autel Nano+.png",
    "lien": "/frontend/src/pages/fiches/Autel Nano+.html",
    "top_du_mois": false,
    "stock": "disponible",
    "tags": [],
    "date_ajout": "2025-08-07"
  },
  {
    "id": "prod_33",
    "nom": "Autel EVO Max 5G",
    "description": "Drone ultraportable 249 g, capteur CMOS 1” 20 MP, vidéo 5.3K/30 fps HDR, LiDAR omnidirectionnel et 38 min d’autonomie.",
    "prix": "À partir de 999 €",
    "categorie": "DRONE",
    "image": "assets/images/Autel EVO Max 5G.png",
    "lien": "/frontend/src/pages/fiches/Autel EVO Max 5G.html",
    "top_du_mois": false,
    "stock": "disponible",
    "tags": [],
    "date_ajout": "2025-08-07"
  },
  {
    "id": "prod_34",
    "nom": "Apple Watch Series 9",
    "description": "Montre intelligente ultra fluide avec gestes tactiles, écran lumineux et puce S9 ultra-rapide.",
    "prix": "449,00 €",
    "categorie": "MONTRE CONNECTE",
    "image": "assets/images/Apple Watch Series 9 stylé.png",
    "lien": "/frontend/src/pages/fiches/AppleWatchSeries9.html",
    "top_du_mois": false,
    "stock": "disponible",
    "tags": [],
    "date_ajout": "2025-08-07"
  },
  {
    "id": "prod_35",
    "nom": "Apple Watch Series 10",
    "description": "Montre connectée haut de gamme avec écran plus grand, capteurs santé avancés et autonomie optimisée.",
    "prix": "À partir de 429 €",
    "categorie": "MONTRE CONNECTE",
    "image": "assets/images/Apple Watch Series 10.png",
    "lien": "/frontend/src/pages/fiches/Apple Watch Series 10.html",
    "top_du_mois": false,
    "stock": "disponible",
    "tags": [],
    "date_ajout": "2025-08-07"
  },
  {
    "id": "prod_36",
    "nom": "HONOR 200 Pro",
    "description": "Smartphone premium avec caméra portrait IA, design élégant et performances photo impressionnantes.",
    "prix": "799,99 €",
    "categorie": "SMARTPHONE",
    "image": "assets/images/HONOR 200 Pro stylé.png",
    "lien": "/frontend/src/pages/fiches/HONOR200Pro.html",
    "top_du_mois": false,
    "stock": "disponible",
    "tags": [],
    "date_ajout": "2025-08-07"
  },
  {
    "id": "prod_37",
    "nom": "PlayStation 5 Slim",
    "description": "Console next-gen compacte, puissante et élégante. Elle réinvente le gaming ultra-performant avec un design plus fin.",
    "prix": "499,00 €",
    "categorie": "CONSOLE",
    "image": "assets/images/PlayStation 5 Slim stylé.png",
    "lien": "/frontend/src/pages/fiches/PlayStation5Slim.html",
    "top_du_mois": false,
    "stock": "disponible",
    "tags": [],
    "date_ajout": "2025-08-07"
  },
  {
    "id": "prod_38",
    "nom": "Samsung Galaxy Tab S10 FE",
    "description": "Tablette polyvalente avec stylet inclus, parfaite pour le travail et les loisirs.",
    "prix": "À partir de 699 €",
    "categorie": "TABLETTE",
    "image": "assets/images/Galaxy Tab S10 FE.png",
    "lien": "/frontend/src/pages/fiches/Samsung Galaxy Tab S10 FE.html",
    "top_du_mois": false,
    "stock": "disponible",
    "tags": [],
    "date_ajout": "2025-08-07"
  },
  {
    "id": "prod_39",
    "nom": "Microsoft Surface Pro X 2025",
    "description": "Tablette hybride haut de gamme sous Windows ARM avec stylet et clavier.",
    "prix": "À partir de 1 199 €",
    "categorie": "TABLETTE",
    "image": "assets/images/Microsoft Surface Pro X 2025.png",
    "lien": "/frontend/src/pages/fiches/Microsoft Surface Pro X 2025.html",
    "top_du_mois": false,
    "stock": "disponible",
    "tags": [],
    "date_ajout": "2025-08-07"
  },
  {
    "id": "prod_40",
    "nom": "Xbox Series X",
    "description": "Console ultra-puissante conçue pour le jeu en 4K, offrant des performances fluides et une immersion totale dans l’univers Xbox.",
    "prix": "499,00 €",
    "categorie": "CONSOLE",
    "image": "assets/images/Xbox Series X.png",
    "lien": "/frontend/src/pages/fiches/Xbox Series X.html",
    "top_du_mois": false,
    "stock": "disponible",
    "tags": [],
    "date_ajout": "2025-08-07"
  }
]